talon_git_labeller/__init__.py
talon_git_labeller/cli.py
talon_git_labeller/commands.py
talon_git_labeller/const.py
talon_git_labeller/helpers.py
talon_git_labeller/write.py
talon_git_labeller-0.1.6.dist-info/LICENSE.txt
talon_git_labeller-0.1.6.dist-info/METADATA
talon_git_labeller-0.1.6.dist-info/WHEEL
talon_git_labeller-0.1.6.dist-info/entry_points.txt
talon_git_labeller-0.1.6.dist-info/top_level.txt
talon_git_labeller-0.1.6.dist-info/RECORD
