Metadata-Version: 2.1
Name: talon-git-labeller
Version: 0.1.6
Summary: Adds items to a talon list when certain git commands are executed, allowing files to be easily selected by voice.
Home-page: https://github.com/mrob95/talon-git-labeller
Author: Mike Roberts
License: MIT
Project-URL: Issues, https://github.com/mrob95/talon_git_labeller/issues
Requires-Python: >=3.7
License-File: LICENSE.txt
